backshell/__init__.py
backshell/__main__.py
backshell-0.1.5.dist-info/entry_points.txt
backshell-0.1.5.dist-info/WHEEL
backshell-0.1.5.dist-info/METADATA
backshell-0.1.5.dist-info/RECORD
